sensor_analysis/__init__.py
sensor_analysis/data_aggregation.py
sensor_analysis/data_loading.py
sensor_analysis/data_merging.py
sensor_analysis/data_metrics.py
sensor_analysis/data_plotting.py
sensor_analysis/data_statistics.py
pysensor_analysis-0.2.dist-info/LICENSE
pysensor_analysis-0.2.dist-info/METADATA
pysensor_analysis-0.2.dist-info/WHEEL
pysensor_analysis-0.2.dist-info/top_level.txt
pysensor_analysis-0.2.dist-info/RECORD
